redoctor/__init__.py
redoctor/checker.py
redoctor/cli.py
redoctor/config.py
redoctor/exceptions.py
redoctor/automaton/__init__.py
redoctor/automaton/checker.py
redoctor/automaton/complexity_analyzer.py
redoctor/automaton/eps_nfa.py
redoctor/automaton/eps_nfa_builder.py
redoctor/automaton/ordered_nfa.py
redoctor/automaton/witness.py
redoctor/diagnostics/__init__.py
redoctor/diagnostics/attack_pattern.py
redoctor/diagnostics/complexity.py
redoctor/diagnostics/diagnostics.py
redoctor/diagnostics/hotspot.py
redoctor/fuzz/__init__.py
redoctor/fuzz/checker.py
redoctor/fuzz/fstring.py
redoctor/fuzz/mutators.py
redoctor/fuzz/seeder.py
redoctor/integrations/__init__.py
redoctor/integrations/source_scanner.py
redoctor/parser/__init__.py
redoctor/parser/ast.py
redoctor/parser/flags.py
redoctor/parser/parser.py
redoctor/recall/__init__.py
redoctor/recall/validator.py
redoctor/unicode/__init__.py
redoctor/unicode/ichar.py
redoctor/unicode/icharset.py
redoctor/unicode/uchar.py
redoctor/unicode/ustring.py
redoctor/vm/__init__.py
redoctor/vm/builder.py
redoctor/vm/inst.py
redoctor/vm/interpreter.py
redoctor/vm/program.py
redoctor-0.1.2.dist-info/licenses/LICENSE
redoctor-0.1.2.dist-info/licenses/LICENSE-MIT
redoctor-0.1.2.dist-info/METADATA
redoctor-0.1.2.dist-info/WHEEL
redoctor-0.1.2.dist-info/entry_points.txt
redoctor-0.1.2.dist-info/top_level.txt
redoctor-0.1.2.dist-info/RECORD
